outscraper_mcp/__init__.py
outscraper_mcp/__main__.py
outscraper_mcp/server.py
outscraper_mcp/server_http.py
mseep_outscraper_mcp-1.0.1.dist-info/METADATA
mseep_outscraper_mcp-1.0.1.dist-info/WHEEL
mseep_outscraper_mcp-1.0.1.dist-info/entry_points.txt
mseep_outscraper_mcp-1.0.1.dist-info/licenses/LICENSE
mseep_outscraper_mcp-1.0.1.dist-info/RECORD
